Satalia_Assignment/Classifier.py
Satalia_Assignment/Fake_Detection.py
Satalia_Assignment/Preprocess.py
Satalia_Assignment/__init__.py
fake_statement_detection-0.2.dist-info/LICENSE
fake_statement_detection-0.2.dist-info/METADATA
fake_statement_detection-0.2.dist-info/WHEEL
fake_statement_detection-0.2.dist-info/top_level.txt
fake_statement_detection-0.2.dist-info/RECORD
